auto_env_loader/__init__.py
auto_env_loader/loader.py
auto_env_loader-0.1.0.dist-info/METADATA
auto_env_loader-0.1.0.dist-info/WHEEL
auto_env_loader-0.1.0.dist-info/top_level.txt
auto_env_loader-0.1.0.dist-info/RECORD
